Workbook
Name Despesa: Categoria!$D$2:$D$11
Name Receita: Categoria!$C$2:$C$6

Sheet Capa
H1: NEXORA
H5: Consultoria Financeira
E9: CONTROLE FINANCEIRO PESSOAL
E12: Controle suas receitas, despesas e alcance seus objetivos financeiros com clareza

Sheet Dashboard
B2: Saldo Atual | G2: Despesas Totais | L2: Orçamento Restante | Q2: Categorias Acima do orçamento | AA2: Moradia | AB2: =SUMIFS(Lançamentos!$E$6:$E$1000,Lançamentos!$C$6:$C$1000,AA2,Lançamentos!$B$6:$B$1000,"Despesa") -> 0 | AD2: Receita | AE2: =SUMIF(Lançamentos!$B:$B,"Receita",Lançamentos!$E:$E) -> 630
C3: =Lançamentos!O24 -> 185 | H3: =Lançamentos!O16 -> 445 | M3: ='Orçamento Mensal'!L19 -> 285 | R3: =COUNTIF('Orçamento Mensal'!E:E,"Acima do Orçamento") -> 2 | AA3: Alimentação | AB3: =SUMIFS(Lançamentos!$E$6:$E$1000,Lançamentos!$C$6:$C$1000,AA3,Lançamentos!$B$6:$B$1000,"Despesa") -> 350 | AD3: Despesa | AE3: =SUMIF(Lançamentos!$B:$B,"Despesa",Lançamentos!$E:$E) -> 445
AA4: Transporte | AB4: =SUMIFS(Lançamentos!$E$6:$E$1000,Lançamentos!$C$6:$C$1000,AA4,Lançamentos!$B$6:$B$1000,"Despesa") -> 20
AA5: Saúde | AB5: =SUMIFS(Lançamentos!$E$6:$E$1000,Lançamentos!$C$6:$C$1000,AA5,Lançamentos!$B$6:$B$1000,"Despesa") -> 0
AA6: Educação | AB6: =SUMIFS(Lançamentos!$E$6:$E$1000,Lançamentos!$C$6:$C$1000,AA6,Lançamentos!$B$6:$B$1000,"Despesa") -> 0
AA7: Lazer | AB7: =SUMIFS(Lançamentos!$E$6:$E$1000,Lançamentos!$C$6:$C$1000,AA7,Lançamentos!$B$6:$B$1000,"Despesa") -> 0
AA8: Compras | AB8: =SUMIFS(Lançamentos!$E$6:$E$1000,Lançamentos!$C$6:$C$1000,AA8,Lançamentos!$B$6:$B$1000,"Despesa") -> 0
AA9: Assinaturas | AB9: =SUMIFS(Lançamentos!$E$6:$E$1000,Lançamentos!$C$6:$C$1000,AA9,Lançamentos!$B$6:$B$1000,"Despesa") -> 75
AA10: Investimentos | AB10: =SUMIFS(Lançamentos!$E$6:$E$1000,Lançamentos!$C$6:$C$1000,AA10,Lançamentos!$B$6:$B$1000,"Despesa") -> 0
AA11: Outros | AB11: =SUMIFS(Lançamentos!$E$6:$E$1000,Lançamentos!$C$6:$C$1000,AA11,Lançamentos!$B$6:$B$1000,"Despesa") -> 0

Sheet Lançamentos
A1: Controle de Receitas e Despesas
A5: Data | B5: Tipo | C5: Categoria | D5: Descrição | E5: Valor | F5: Forma de Pagamento | G5: Status
B6: Receita | C6: Investimentos | E6: 500
B7: Receita | C7: Freelance | E7: 130
B8: Despesa | C8: Alimentação | E8: 350 | N8: Receitas Totais
B9: Despesa | C9: Assinaturas | E9: 75 | O9: =SUMIF(B:B,"Receita",E:E) -> 630
B10: Despesa | C10: Transporte | E10: 20
N15: Despesas Totais
O16: =SUMIF(B:B,"Despesa",E:E) -> 445
N23: Saldo Atual
O24: =O9-O16 -> 185

Sheet Orçamento Mensal
A1: "Planeje seus gastos e acompanhe seu desempenho financeiro."
A5: Categoria | B5: Orçamento | C5: Gasto Real | D5: Diferença | E5: Status
A6: Moradia | C6: =IF(A6="","",SUMIFS(Lançamentos!$E:$E,Lançamentos!$C:$C,A6,Lançamentos!$B:$B,"Despesa")) -> 0 | D6: =IF(A6="","",B6-C6) -> 0 | E6: =IF(A6="","",IF(C6>B6,"Acima do Orçamento","Dentro do Orçamento")) -> Dentro do Orçamento | K6: Orçamento Total
A7: Alimentação | B7: 700 | C7: =IF(A7="","",SUMIFS(Lançamentos!$E:$E,Lançamentos!$C:$C,A7,Lançamentos!$B:$B,"Despesa")) -> 350 | D7: =IF(A7="","",B7-C7) -> 350 | E7: =IF(A7="","",IF(C7>B7,"Acima do Orçamento","Dentro do Orçamento")) -> Dentro do Orçamento | L7: =SUM(B6:B505) -> 1030
A8: Transporte | B8: 30 | C8: =IF(A8="","",SUMIFS(Lançamentos!$E:$E,Lançamentos!$C:$C,A8,Lançamentos!$B:$B,"Despesa")) -> 20 | D8: =IF(A8="","",B8-C8) -> 10 | E8: =IF(A8="","",IF(C8>B8,"Acima do Orçamento","Dentro do Orçamento")) -> Dentro do Orçamento
A9: Saúde | C9: =IF(A9="","",SUMIFS(Lançamentos!$E:$E,Lançamentos!$C:$C,A9,Lançamentos!$B:$B,"Despesa")) -> 0 | D9: =IF(A9="","",B9-C9) -> 0 | E9: =IF(A9="","",IF(C9>B9,"Acima do Orçamento","Dentro do Orçamento")) -> Dentro do Orçamento
A10: Educação | C10: =IF(A10="","",SUMIFS(Lançamentos!$E:$E,Lançamentos!$C:$C,A10,Lançamentos!$B:$B,"Despesa")) -> 0 | D10: =IF(A10="","",B10-C10) -> 0 | E10: =IF(A10="","",IF(C10>B10,"Acima do Orçamento","Dentro do Orçamento")) -> Dentro do Orçamento
A11: Lazer | B11: 250 | C11: 300 | D11: =IF(A11="","",B11-C11) -> -50 | E11: =IF(A11="","",IF(C11>B11,"Acima do Orçamento","Dentro do Orçamento")) -> Acima do Orçamento
A12: Compras | B12: 50 | C12: =IF(A12="","",SUMIFS(Lançamentos!$E:$E,Lançamentos!$C:$C,A12,Lançamentos!$B:$B,"Despesa")) -> 0 | D12: =IF(A12="","",B12-C12) -> 50 | E12: =IF(A12="","",IF(C12>B12,"Acima do Orçamento","Dentro do Orçamento")) -> Dentro do Orçamento | K12: Gasto Total
A13: Assinaturas | C13: =IF(A13="","",SUMIFS(Lançamentos!$E:$E,Lançamentos!$C:$C,A13,Lançamentos!$B:$B,"Despesa")) -> 75 | D13: =IF(A13="","",B13-C13) -> -75 | E13: =IF(A13="","",IF(C13>B13,"Acima do Orçamento","Dentro do Orçamento")) -> Acima do Orçamento | L13: =SUM(C6:C505) -> 745
A14: Investimentos | C14: =IF(A14="","",SUMIFS(Lançamentos!$E:$E,Lançamentos!$C:$C,A14,Lançamentos!$B:$B,"Despesa")) -> 0 | D14: =IF(A14="","",B14-C14) -> 0 | E14: =IF(A14="","",IF(C14>B14,"Acima do Orçamento","Dentro do Orçamento")) -> Dentro do Orçamento
A15: Outros | C15: =IF(A15="","",SUMIFS(Lançamentos!$E:$E,Lançamentos!$C:$C,A15,Lançamentos!$B:$B,"Despesa")) -> 0 | D15: =IF(A15="","",B15-C15) -> 0 | E15: =IF(A15="","",IF(C15>B15,"Acima do Orçamento","Dentro do Orçamento")) -> Dentro do Orçamento
C16: =IF(A16="","",SUMIFS(Lançamentos!$E:$E,Lançamentos!$C:$C,A16,Lançamentos!$B:$B,"Despesa")) | D16: =IF(A16="","",B16-C16) | E16: =IF(A16="","",IF(C16>B16,"Acima do Orçamento","Dentro do Orçamento"))
C17: =IF(A17="","",SUMIFS(Lançamentos!$E:$E,Lançamentos!$C:$C,A17,Lançamentos!$B:$B,"Despesa")) | D17: =IF(A17="","",B17-C17) | E17: =IF(A17="","",IF(C17>B17,"Acima do Orçamento","Dentro do Orçamento"))
C18: =IF(A18="","",SUMIFS(Lançamentos!$E:$E,Lançamentos!$C:$C,A18,Lançamentos!$B:$B,"Despesa")) | D18: =IF(A18="","",B18-C18) | E18: =IF(A18="","",IF(C18>B18,"Acima do Orçamento","Dentro do Orçamento")) | K18: Saldo do Orçamento
C19: =IF(A19="","",SUMIFS(Lançamentos!$E:$E,Lançamentos!$C:$C,A19,Lançamentos!$B:$B,"Despesa")) | D19: =IF(A19="","",B19-C19) | E19: =IF(A19="","",IF(C19>B19,"Acima do Orçamento","Dentro do Orçamento")) | L19: =L7-L13 -> 285
C20: =IF(A20="","",SUMIFS(Lançamentos!$E:$E,Lançamentos!$C:$C,A20,Lançamentos!$B:$B,"Despesa")) | D20: =IF(A20="","",B20-C20) | E20: =IF(A20="","",IF(C20>B20,"Acima do Orçamento","Dentro do Orçamento"))
C21: =IF(A21="","",SUMIFS(Lançamentos!$E:$E,Lançamentos!$C:$C,A21,Lançamentos!$B:$B,"Despesa")) | D21: =IF(A21="","",B21-C21) | E21: =IF(A21="","",IF(C21>B21,"Acima do Orçamento","Dentro do Orçamento"))
C22: =IF(A22="","",SUMIFS(Lançamentos!$E:$E,Lançamentos!$C:$C,A22,Lançamentos!$B:$B,"Despesa")) | D22: =IF(A22="","",B22-C22) | E22: =IF(A22="","",IF(C22>B22,"Acima do Orçamento","Dentro do Orçamento"))
C23: =IF(A23="","",SUMIFS(Lançamentos!$E:$E,Lançamentos!$C:$C,A23,Lançamentos!$B:$B,"Despesa")) | D23: =IF(A23="","",B23-C23) | E23: =IF(A23="","",IF(C23>B23,"Acima do Orçamento","Dentro do Orçamento"))
C24: =IF(A24="","",SUMIFS(Lançamentos!$E:$E,Lançamentos!$C:$C,A24,Lançamentos!$B:$B,"Despesa")) | D24: =IF(A24="","",B24-C24) | E24: =IF(A24="","",IF(C24>B24,"Acima do Orçamento","Dentro do Orçamento")) | K24: Orçamento Utilizado
C25: =IF(A25="","",SUMIFS(Lançamentos!$E:$E,Lançamentos!$C:$C,A25,Lançamentos!$B:$B,"Despesa")) | D25: =IF(A25="","",B25-C25) | E25: =IF(A25="","",IF(C25>B25,"Acima do Orçamento","Dentro do Orçamento")) | L25: =L13/L7 -> 0.72330097
C26: =IF(A26="","",SUMIFS(Lançamentos!$E:$E,Lançamentos!$C:$C,A26,Lançamentos!$B:$B,"Despesa")) | D26: =IF(A26="","",B26-C26) | E26: =IF(A26="","",IF(C26>B26,"Acima do Orçamento","Dentro do Orçamento"))
C27: =IF(A27="","",SUMIFS(Lançamentos!$E:$E,Lançamentos!$C:$C,A27,Lançamentos!$B:$B,"Despesa")) | D27: =IF(A27="","",B27-C27) | E27: =IF(A27="","",IF(C27>B27,"Acima do Orçamento","Dentro do Orçamento"))
C28: =IF(A28="","",SUMIFS(Lançamentos!$E:$E,Lançamentos!$C:$C,A28,Lançamentos!$B:$B,"Despesa")) | D28: =IF(A28="","",B28-C28) | E28: =IF(A28="","",IF(C28>B28,"Acima do Orçamento","Dentro do Orçamento"))
C29: =IF(A29="","",SUMIFS(Lançamentos!$E:$E,Lançamentos!$C:$C,A29,Lançamentos!$B:$B,"Despesa")) | D29: =IF(A29="","",B29-C29) | E29: =IF(A29="","",IF(C29>B29,"Acima do Orçamento","Dentro do Orçamento"))
C30: =IF(A30="","",SUMIFS(Lançamentos!$E:$E,Lançamentos!$C:$C,A30,Lançamentos!$B:$B,"Despesa")) | D30: =IF(A30="","",B30-C30) | E30: =IF(A30="","",IF(C30>B30,"Acima do Orçamento","Dentro do Orçamento"))
C31: =IF(A31="","",SUMIFS(Lançamentos!$E:$E,Lançamentos!$C:$C,A31,Lançamentos!$B:$B,"Despesa")) | D31: =IF(A31="","",B31-C31) | E31: =IF(A31="","",IF(C31>B31,"Acima do Orçamento","Dentro do Orçamento"))
C32: =IF(A32="","",SUMIFS(Lançamentos!$E:$E,Lançamentos!$C:$C,A32,Lançamentos!$B:$B,"Despesa")) | D32: =IF(A32="","",B32-C32) | E32: =IF(A32="","",IF(C32>B32,"Acima do Orçamento","Dentro do Orçamento"))
C33: =IF(A33="","",SUMIFS(Lançamentos!$E:$E,Lançamentos!$C:$C,A33,Lançamentos!$B:$B,"Despesa")) | D33: =IF(A33="","",B33-C33) | E33: =IF(A33="","",IF(C33>B33,"Acima do Orçamento","Dentro do Orçamento"))
C34: =IF(A34="","",SUMIFS(Lançamentos!$E:$E,Lançamentos!$C:$C,A34,Lançamentos!$B:$B,"Despesa")) | D34: =IF(A34="","",B34-C34) | E34: =IF(A34="","",IF(C34>B34,"Acima do Orçamento","Dentro do Orçamento"))
C35: =IF(A35="","",SUMIFS(Lançamentos!$E:$E,Lançamentos!$C:$C,A35,Lançamentos!$B:$B,"Despesa")) | D35: =IF(A35="","",B35-C35) | E35: =IF(A35="","",IF(C35>B35,"Acima do Orçamento","Dentro do Orçamento"))
C36: =IF(A36="","",SUMIFS(Lançamentos!$E:$E,Lançamentos!$C:$C,A36,Lançamentos!$B:$B,"Despesa")) | D36: =IF(A36="","",B36-C36) | E36: =IF(A36="","",IF(C36>B36,"Acima do Orçamento","Dentro do Orçamento"))
C37: =IF(A37="","",SUMIFS(Lançamentos!$E:$E,Lançamentos!$C:$C,A37,Lançamentos!$B:$B,"Despesa")) | D37: =IF(A37="","",B37-C37) | E37: =IF(A37="","",IF(C37>B37,"Acima do Orçamento","Dentro do Orçamento"))
... C505: =IF(A505="","",SUMIFS(Lançamentos!$E:$E,Lançamentos!$C:$C,A505,Lançamentos!$B:$B,"Despesa")) | D505: =IF(A505="","",B505-C505) | E505: =IF(A505="","",IF(C505>B505,"Acima do Orçamento","Dentro do Orçamento"))

Sheet Categoria
A2: Receita | C2: Salário | D2: Moradia | F2: PIX | H2: Pago
A3: Despesa | C3: Freelance | D3: Alimentação | F3: Dinheiro | H3: Pendente
C4: Investimentos | D4: Transporte | F4: Débito
C5: Comissões | D5: Saúde | F5: Crédito
C6: Outros | D6: Educação | F6: Transferência
D7: Lazer
D8: Compras
D9: Assinaturas
D10: Investimentos
D11: Outros
