Workbook

Sheet Capa
H1: NEXORA
H5: Consultoria Financeira
F9: FLUXO DE CAIXA PROFISSIONAL
F12: Controle financeiro inteligente para empresas e profissionais autônomos

Sheet Dashboard
A1: DASHBOARD FINANCEIRO | AD1: Indicador | AE1: Valor | AH1: Meta | AI1: 3000 | AK1: A pagar | AL1: =SUM(Pagar!E:E) -> 1270
AA2: Marketing | AB2: =SUMIFS(Lançamentos!E:E,Lançamentos!C:C,AA2) -> 0 | AD2: Receitas | AE2: =Indicadores!B2 -> 2900 | AH2: Atual | AI2: =Indicadores!B4 -> 1250 | AK2: A receber | AL2: =SUM(Receber!E:E) -> 760
AA3: Salários | AB3: =SUMIFS(Lançamentos!E:E,Lançamentos!C:C,AA3) -> 0 | AD3: Despesas | AE3: =Indicadores!B3 -> 1650 | AH3: Progresso | AI3: =AI2/AI1 -> 0.41666667
B4: RECEITAS | G4: DESPESAS | L4: SALDO | Q4: MARGEM | AA4: Impostos | AB4: =SUMIFS(Lançamentos!E:E,Lançamentos!C:C,AA4) -> 750
C5: =Indicadores!B2 -> 2900 | H5: =Indicadores!B3 -> 1650 | M5: =Indicadores!B4 -> 1250 | R5: =Indicadores!B10 -> 0.43103448 | AA5: Fornecedores | AB5: =SUMIFS(Lançamentos!E:E,Lançamentos!C:C,AA5) -> 900
AA6: Aluguel | AB6: =SUMIFS(Lançamentos!E:E,Lançamentos!C:C,AA6) -> 0
AA7: Internet | AB7: =SUMIFS(Lançamentos!E:E,Lançamentos!C:C,AA7) -> 0
AA8: Transporte | AB8: =SUMIFS(Lançamentos!E:E,Lançamentos!C:C,AA8) -> 0
AA9: Outros | AB9: =SUMIFS(Lançamentos!E:E,Lançamentos!C:C,AA9) -> 400
B23: Meta Financeira | J23: Meta | R23: Alerta
B24: Meta: | C24: =Dashboard!AI1 -> 3000 | H24: =AI2/AI1 -> 0.41666667 | Q24: Contas a | R24: Pagar: | S24: =Dashboard!AL1 -> 1270
B25: Atual: | C25: =Dashboard!AI2 -> 1250 | Q25: Contas a | R25: Receber: | S25: =Dashboard!AL2 -> 760
B26: Progresso: | C26: =Dashboard!AI3 -> 0.41666667

Sheet Lançamentos
A1: Data | B1: Tipo | C1: Categoria | D1: Descrição | E1: Valor | F1: Forma de pagamento | G1: Observações | H1: Mês
A2: 45721 | B2: Receita | C2: Serviços | E2: 500 | H2: =IF(A2="","",PROPER(TEXT(A2,"mmmm"))) -> Março
A3: 45902 | B3: Despesa | C3: Impostos | E3: 750 | H3: =IF(A3="","",PROPER(TEXT(A3,"mmmm"))) -> Setembro
A4: 46031 | B4: Receita | C4: Investimentos | E4: 2000 | H4: =IF(A4="","",PROPER(TEXT(A4,"mmmm"))) -> Janeiro
A5: 46152 | B5: Despesa | C5: Fornecedores | E5: 900 | H5: =IF(A5="","",PROPER(TEXT(A5,"mmmm"))) -> Maio
A6: 46181 | B6: Receita | C6: Outros | E6: 400 | H6: =IF(A6="","",PROPER(TEXT(A6,"mmmm"))) -> Junho
H7: =IF(A7="","",PROPER(TEXT(A7,"mmmm")))
H8: =IF(A8="","",PROPER(TEXT(A8,"mmmm")))
H9: =IF(A9="","",PROPER(TEXT(A9,"mmmm")))
H10: =IF(A10="","",PROPER(TEXT(A10,"mmmm")))
H11: =IF(A11="","",PROPER(TEXT(A11,"mmmm")))
H12: =IF(A12="","",PROPER(TEXT(A12,"mmmm")))
H13: =IF(A13="","",PROPER(TEXT(A13,"mmmm")))
H14: =IF(A14="","",PROPER(TEXT(A14,"mmmm")))
H15: =IF(A15="","",PROPER(TEXT(A15,"mmmm")))
H16: =IF(A16="","",PROPER(TEXT(A16,"mmmm")))
H17: =IF(A17="","",PROPER(TEXT(A17,"mmmm")))
H18: =IF(A18="","",PROPER(TEXT(A18,"mmmm")))
... H100: =IF(A100="","",PROPER(TEXT(A100,"mmmm")))

Sheet Categoria
A1: Tipo | B1: Categoria
A2: Receita | B2: Vendas
A3: Receita | B3: Serviços
A4: Receita | B4: Comissões
A5: Receita | B5: Investimentos
A6: Receita | B6: Outros
A7: Despesa | B7: Marketing
A8: Despesa | B8: Salários
A9: Despesa | B9: Impostos
A10: Despesa | B10: Fornecedores
A11: Despesa | B11: Aluguel
A12: Despesa | B12: Internet
... A14: Despesa | B14: Outros

Sheet Pagar
A1: Vencimento | B1: Fornecedor | C1: Categoria | D1: Descrição | E1: Valor | F1: Status | G1: Data de Pagamento
C2: Internet | E2: 70 | F2: Pago
C3: Aluguel | E3: 800 | F3: Pago
C4: Salários | E4: 400 | F4: Pendente
F5: Atrasado

Sheet Receber
A1: Vencimento | B1: Cliente | C1: Categoria | D1: Descrição | E1: Valor | F1: Status | G1: Data de Recebimento
C2: Comissões | E2: 60 | F2: Pendente
C3: Investimentos | E3: 700 | F3: Recebido
F4: Atrasado

Sheet Indicadores
A1: Indicador | B1: Valor
A2: Receita Total | B2: =SUMIFS(Lançamentos!E:E,Lançamentos!B:B,"Receita") -> 2900
A3: Despesa Total | B3: =SUMIFS(Lançamentos!E:E,Lançamentos!B:B,"Despesa") -> 1650
A4: Saldo | B4: =B2-B3 -> 1250
A5: Contas a Pagar | B5: =SUMIFS(Pagar!E:E,Pagar!F:F,"Pendente") -> 400
A6: Contas a Receber | B6: =SUMIFS(Receber!E:E,Receber!F:F,"Pendente") -> 60
A7: Total Recebido | B7: =SUMIFS(Receber!E:E,Receber!F:F,"Recebido") -> 700
A8: Total Pago | B8: =SUMIFS(Pagar!E:E,Pagar!F:F,"Pago") -> 870
A9: Lucro Líquido | B9: =B2-B3 -> 1250
A10: Margem | B10: =IF(B2=0,0,B9/B2) -> 0.43103448
