Workbook
Name Despesa: Configurações!$C$2:$C$10
Name Receita: Configurações!$A$2:$A$7

Sheet Capa
H1: NEXORA
H5: Consultoria Financeira
F9: ORÇAMENTO EMPRESARIAL
D12: Controle seu orçamento, acompanhe seus resultados e impulsione o crescimento do seu negócio!

Sheet Dashboard
A1: NEXORA
A2: Dashboard Financeiro | AA2: Receita | AB2: =SUMIF(Realizado!C:C,"Receita",Realizado!E:E) -> 200 | AD2: Marketing | AE2: =SUMIF(Realizado!D:D,"Marketing",Realizado!E:E) -> 0
A3: Visão geral do desempenho financeiro | AA3: Despesa | AB3: =SUMIF(Realizado!C:C,"Despesa",Realizado!E:E) -> 155 | AD3: Salários | AE3: =SUMIF(Realizado!D:D,"Salários",Realizado!E:E) -> 0
AD4: Aluguel | AE4: =SUMIF(Realizado!D:D,"Aluguel",Realizado!E:E) -> 0
AD5: Internet | AE5: =SUMIF(Realizado!D:D,"Internet",Realizado!E:E) -> 75
B6: Receita Total | G6: Despesa Total | L6: Resultado (Lucro/Prejuízo) | Q6: Aderência ao Orçamento | AD6: Energia | AE6: =SUMIF(Realizado!D:D,"Energia",Realizado!E:E) -> 80
C7: =SUM(Realizado!E:E) -> 355 | H7: =SUMIF(Realizado!C:C,"Despesa",Realizado!E:E) -> 155 | M7: =SUMIF(Realizado!C:C,"Receita",Realizado!E:E)-SUMIF(Realizado!C:C,"Despesa",Realizado!E:E) -> 45 | R7: =IF(SUM('Orçamento Anual'!D:D)=0,"",SUM(Realizado!E:E)/SUM('Orçamento Anual'!D:D)) -> 0.48630137 | AD7: Impostos | AE7: =SUMIF(Realizado!D:D,"Impostos",Realizado!E:E) -> 0
AD8: Transporte | AE8: =SUMIF(Realizado!D:D,"Transporte",Realizado!E:E) -> 0
AD9: Fornecedores | AE9: =SUMIF(Realizado!D:D,"Fornecedores",Realizado!E:E) -> 0
AD10: Outras Despesas | AE10: =SUMIF(Realizado!D:D,"Outras Despesas",Realizado!E:E) -> 0
F26: \

Sheet Orçamento Anual
A1: Mês | B1: Categoria | C1: Tipo | D1: Valor Orçado
B2: Energia | C2: Despesa | D2: 80
B3: Serviços | C3: Receita | D3: 500
B4: Vendas | C4: Receita | D4: 150

Sheet Realizado
A1: Data | B1: Mês | C1: Tipo | D1: Categoria | E1: Valor Real
C2: Receita | D2: Vendas | E2: 200
C3: Despesa | D3: Internet | E3: 75
C4: Despesa | D4: Energia | E4: 80
L5: Receitas Realizadas
M7: =SUMIF(C:C,"Receita",E:E) -> 200
L13: Despesas Realizadas
M15: =SUMIF(C:C,"Despesa",E:E) -> 155
L21: Saldo Real
M23: =SUMIF(C:C,"Receita",E:E)-SUMIF(C:C,"Despesa",E:E) -> 45

Sheet Comparativo
A1: Categoria | B1: Orçado | C1: Realizado | D1: Diferença
A2: Marketing | B2: =IF(A2="","",SUMIF('Orçamento Anual'!B:B,A2,'Orçamento Anual'!D:D)) -> 0 | C2: =IF(A2="","",SUMIF(Realizado!D:D,A2,Realizado!E:E)) -> 0 | D2: =IF(A2="","",C2-B2) -> 0
A3: Salários | B3: =IF(A3="","",SUMIF('Orçamento Anual'!B:B,A3,'Orçamento Anual'!D:D)) -> 0 | C3: =IF(A3="","",SUMIF(Realizado!D:D,A3,Realizado!E:E)) -> 0 | D3: =IF(A3="","",C3-B3) -> 0
A4: Aluguel | B4: =IF(A4="","",SUMIF('Orçamento Anual'!B:B,A4,'Orçamento Anual'!D:D)) -> 0 | C4: =IF(A4="","",SUMIF(Realizado!D:D,A4,Realizado!E:E)) -> 0 | D4: =IF(A4="","",C4-B4) -> 0
A5: Internet | B5: =IF(A5="","",SUMIF('Orçamento Anual'!B:B,A5,'Orçamento Anual'!D:D)) -> 0 | C5: =IF(A5="","",SUMIF(Realizado!D:D,A5,Realizado!E:E)) -> 75 | D5: =IF(A5="","",C5-B5) -> 75
A6: Energia | B6: =IF(A6="","",SUMIF('Orçamento Anual'!B:B,A6,'Orçamento Anual'!D:D)) -> 80 | C6: =IF(A6="","",SUMIF(Realizado!D:D,A6,Realizado!E:E)) -> 80 | D6: =IF(A6="","",C6-B6) -> 0
A7: Impostos | B7: =IF(A7="","",SUMIF('Orçamento Anual'!B:B,A7,'Orçamento Anual'!D:D)) -> 0 | C7: =IF(A7="","",SUMIF(Realizado!D:D,A7,Realizado!E:E)) -> 0 | D7: =IF(A7="","",C7-B7) -> 0
A8: Transporte | B8: =IF(A8="","",SUMIF('Orçamento Anual'!B:B,A8,'Orçamento Anual'!D:D)) -> 0 | C8: =IF(A8="","",SUMIF(Realizado!D:D,A8,Realizado!E:E)) -> 0 | D8: =IF(A8="","",C8-B8) -> 0 | G8: Total Orçado | M8: Total Realizado
A9: Fornecedores | B9: =IF(A9="","",SUMIF('Orçamento Anual'!B:B,A9,'Orçamento Anual'!D:D)) -> 0 | C9: =IF(A9="","",SUMIF(Realizado!D:D,A9,Realizado!E:E)) -> 0 | D9: =IF(A9="","",C9-B9) -> 0
A10: Outras Despesas | B10: =IF(A10="","",SUMIF('Orçamento Anual'!B:B,A10,'Orçamento Anual'!D:D)) -> 0 | C10: =IF(A10="","",SUMIF(Realizado!D:D,A10,Realizado!E:E)) -> 0 | D10: =IF(A10="","",C10-B10) -> 0 | H10: =SUM(B:B) -> 730 | N10: =SUM(C:C) -> 355
A11: Vendas | B11: =IF(A11="","",SUMIF('Orçamento Anual'!B:B,A11,'Orçamento Anual'!D:D)) -> 150 | C11: =IF(A11="","",SUMIF(Realizado!D:D,A11,Realizado!E:E)) -> 200 | D11: =IF(A11="","",C11-B11) -> 50
A12: Serviços | B12: =IF(A12="","",SUMIF('Orçamento Anual'!B:B,A12,'Orçamento Anual'!D:D)) -> 500 | C12: =IF(A12="","",SUMIF(Realizado!D:D,A12,Realizado!E:E)) -> 0 | D12: =IF(A12="","",C12-B12) -> -500
A13: Consultorias | B13: =IF(A13="","",SUMIF('Orçamento Anual'!B:B,A13,'Orçamento Anual'!D:D)) -> 0 | C13: =IF(A13="","",SUMIF(Realizado!D:D,A13,Realizado!E:E)) -> 0 | D13: =IF(A13="","",C13-B13) -> 0
A14: Comissões | B14: =IF(A14="","",SUMIF('Orçamento Anual'!B:B,A14,'Orçamento Anual'!D:D)) -> 0 | C14: =IF(A14="","",SUMIF(Realizado!D:D,A14,Realizado!E:E)) -> 0 | D14: =IF(A14="","",C14-B14) -> 0
A15: Investimentos | B15: =IF(A15="","",SUMIF('Orçamento Anual'!B:B,A15,'Orçamento Anual'!D:D)) -> 0 | C15: =IF(A15="","",SUMIF(Realizado!D:D,A15,Realizado!E:E)) -> 0 | D15: =IF(A15="","",C15-B15) -> 0
A16: Outras Receitas | B16: =IF(A16="","",SUMIF('Orçamento Anual'!B:B,A16,'Orçamento Anual'!D:D)) -> 0 | C16: =IF(A16="","",SUMIF(Realizado!D:D,A16,Realizado!E:E)) -> 0 | D16: =IF(A16="","",C16-B16) -> 0
B17: =IF(A17="","",SUMIF('Orçamento Anual'!B:B,A17,'Orçamento Anual'!D:D)) | C17: =IF(A17="","",SUMIF(Realizado!D:D,A17,Realizado!E:E)) | D17: =IF(A17="","",C17-B17)
B18: =IF(A18="","",SUMIF('Orçamento Anual'!B:B,A18,'Orçamento Anual'!D:D)) | C18: =IF(A18="","",SUMIF(Realizado!D:D,A18,Realizado!E:E)) | D18: =IF(A18="","",C18-B18) | G18: Diferença Total | M18: Aderência ao Orçamento
B19: =IF(A19="","",SUMIF('Orçamento Anual'!B:B,A19,'Orçamento Anual'!D:D)) | C19: =IF(A19="","",SUMIF(Realizado!D:D,A19,Realizado!E:E)) | D19: =IF(A19="","",C19-B19)
B20: =IF(A20="","",SUMIF('Orçamento Anual'!B:B,A20,'Orçamento Anual'!D:D)) | C20: =IF(A20="","",SUMIF(Realizado!D:D,A20,Realizado!E:E)) | D20: =IF(A20="","",C20-B20) | H20: =SUM(D:D) -> -375 | N20: =IF(SUM(B:B)=0,"",SUM(C:C)/SUM(B:B)) -> 0.48630137
B21: =IF(A21="","",SUMIF('Orçamento Anual'!B:B,A21,'Orçamento Anual'!D:D)) | C21: =IF(A21="","",SUMIF(Realizado!D:D,A21,Realizado!E:E)) | D21: =IF(A21="","",C21-B21)
B22: =IF(A22="","",SUMIF('Orçamento Anual'!B:B,A22,'Orçamento Anual'!D:D)) | C22: =IF(A22="","",SUMIF(Realizado!D:D,A22,Realizado!E:E)) | D22: =IF(A22="","",C22-B22)
B23: =IF(A23="","",SUMIF('Orçamento Anual'!B:B,A23,'Orçamento Anual'!D:D)) | C23: =IF(A23="","",SUMIF(Realizado!D:D,A23,Realizado!E:E)) | D23: =IF(A23="","",C23-B23)
B24: =IF(A24="","",SUMIF('Orçamento Anual'!B:B,A24,'Orçamento Anual'!D:D)) | C24: =IF(A24="","",SUMIF(Realizado!D:D,A24,Realizado!E:E)) | D24: =IF(A24="","",C24-B24)
B25: =IF(A25="","",SUMIF('Orçamento Anual'!B:B,A25,'Orçamento Anual'!D:D)) | C25: =IF(A25="","",SUMIF(Realizado!D:D,A25,Realizado!E:E)) | D25: =IF(A25="","",C25-B25)
B26: =IF(A26="","",SUMIF('Orçamento Anual'!B:B,A26,'Orçamento Anual'!D:D)) | C26: =IF(A26="","",SUMIF(Realizado!D:D,A26,Realizado!E:E)) | D26: =IF(A26="","",C26-B26)
B27: =IF(A27="","",SUMIF('Orçamento Anual'!B:B,A27,'Orçamento Anual'!D:D)) | C27: =IF(A27="","",SUMIF(Realizado!D:D,A27,Realizado!E:E)) | D27: =IF(A27="","",C27-B27)
B28: =IF(A28="","",SUMIF('Orçamento Anual'!B:B,A28,'Orçamento Anual'!D:D)) | C28: =IF(A28="","",SUMIF(Realizado!D:D,A28,Realizado!E:E)) | D28: =IF(A28="","",C28-B28)
B29: =IF(A29="","",SUMIF('Orçamento Anual'!B:B,A29,'Orçamento Anual'!D:D)) | C29: =IF(A29="","",SUMIF(Realizado!D:D,A29,Realizado!E:E)) | D29: =IF(A29="","",C29-B29)
B30: =IF(A30="","",SUMIF('Orçamento Anual'!B:B,A30,'Orçamento Anual'!D:D)) | C30: =IF(A30="","",SUMIF(Realizado!D:D,A30,Realizado!E:E)) | D30: =IF(A30="","",C30-B30)
B31: =IF(A31="","",SUMIF('Orçamento Anual'!B:B,A31,'Orçamento Anual'!D:D)) | C31: =IF(A31="","",SUMIF(Realizado!D:D,A31,Realizado!E:E)) | D31: =IF(A31="","",C31-B31)
B32: =IF(A32="","",SUMIF('Orçamento Anual'!B:B,A32,'Orçamento Anual'!D:D)) | C32: =IF(A32="","",SUMIF(Realizado!D:D,A32,Realizado!E:E)) | D32: =IF(A32="","",C32-B32)
... B501: =IF(A501="","",SUMIF('Orçamento Anual'!B:B,A501,'Orçamento Anual'!D:D)) | C501: =IF(A501="","",SUMIF(Realizado!D:D,A501,Realizado!E:E)) | D501: =IF(A501="","",C501-B501)

Sheet Configurações
A1: RECEITAS | C1: DESPESAS
A2: Vendas | C2: Marketing
A3: Serviços | C3: Salários
A4: Consultorias | C4: Aluguel
A5: Comissões | C5: Internet
A6: Investimentos | C6: Energia
A7: Outras Receitas | C7: Impostos
C8: Transporte
C9: Fornecedores
C10: Outras Despesas
