Workbook

Sheet Capa
H1: NEXORA
H5: Consultoria Financeira
E9: ORGANIZAÇÃO FINANCEIRA PESSOAL
D12: Conheça seu patrimônio, controle suas dívidas e acompanhe sua evolução financeira

Sheet Dashboard
A1: Dashboard Financeiro Pessoal
K2: Visualize sua situação financeira em um único lugar! | AA2: Dinheiro | AB2: =SUMIF(Patrimônio!B9:B38,"Dinheiro",Patrimônio!D9:D38) -> 0 | AD2: Renda Fixa | AE2: =SUMIF(Investimentos!B9:B38,"Renda Fixa",Investimentos!F9:F38) -> 0
AA3: Investimento | AB3: =SUMIF(Patrimônio!B9:B38,"Investimento",Patrimônio!D9:D38) -> 1500 | AD3: Tesouro Direto | AE3: =SUMIF(Investimentos!B9:B38,"Tesouro Direto",Investimentos!F9:F38) -> 70
AA4: Veículo | AB4: =SUMIF(Patrimônio!B9:B38,"Veículo",Patrimônio!D9:D38) -> 750 | AD4: Ações | AE4: =SUMIF(Investimentos!B9:B38,"Ações",Investimentos!F9:F38) -> 100
B5: Patrimonio Liquido | G5: Total Investido | L5: Ganho/Perda Total | Q5: Quantidade de Investimento | AA5: Imóvel | AB5: =SUMIF(Patrimônio!B9:B38,"Imóvel",Patrimônio!D9:D38) -> 2000 | AD5: Fundos Imobiliários | AE5: =SUMIF(Investimentos!B9:B38,"Fundos Imobiliários",Investimentos!F9:F38) -> 180
AA6: Outros Bens | AB6: =SUMIF(Patrimônio!B9:B38,"Outros Bens",Patrimônio!D9:D38) -> 250 | AD6: ETFs | AE6: =SUMIF(Investimentos!B9:B38,"ETFs",Investimentos!F9:F38) -> 450
C7: =H13 -> 2500 | H7: =O11 -> 2160 | M7: =O13 -> 2640 | R7: =O14 -> 5 | AD7: Criptomoedas | AE7: =SUMIF(Investimentos!B9:B38,"Criptomoedas",Investimentos!F9:F38) -> 4000
AD8: Poupança | AE8: =SUMIF(Investimentos!B9:B38,"Poupança",Investimentos!F9:F38) -> 0
AD9: Outros | AE9: =SUMIF(Investimentos!B9:B38,"Outros",Investimentos!F9:F38) -> 0
E10: Resumo Patrimonial | L10: Resumo dos Investimentos
E11: Total de Ativos | H11: =Patrimônio!D5 -> 4500 | L11: Total Investido | O11: =Investimentos!M11 -> 2160
E12: Total de Passivos | H12: =Patrimônio!L5 -> 2000 | L12: Valor Atual | O12: =Investimentos!M17 -> 4800
E13: Patrimonio Liquido | H13: =Patrimônio!H5 -> 2500 | L13: Ganho/Perda Total | O13: =Investimentos!M23 -> 2640
E14: Total Investido | H14: =Investimentos!M11 -> 2160 | L14: Quantidade de Investimento | O14: =COUNTA(Investimentos!E9:E38) -> 5
E15: Valor Atual dos Investimentos | H15: =Investimentos!M17 -> 4800

Sheet Patrimônio
A1: Patrimônio | S1: =SUM(D9:D38) -> 4500 | T1: =SUM(L9:L38) -> 2000
D4: Total de Ativos | G4: Patrimônio Líquido | L4: Total de Passivos
D5: =SUM(D9:D38) -> 4500 | H5: =D5-L5 -> 2500 | L5: =SUM(L9:L38) -> 2000
B7: ATIVOS | J7: PASSIVOS
B8: Categoria | C8: Descrição | D8: Valor | E8: Data de Atualização | F8: % do Patrimônio | J8: Categoria | K8: Descrição | L8: Valor devido | M8: Data de Atualização | N8: % das Dívidas
F9: =IF($S$1=0,0,D9/$S$1) -> 0 | J9: Empréstimo | L9: 1000 | N9: =IF($T$1=0,0,L9/$T$1) -> 0.5
F10: =IF($S$1=0,0,D10/$S$1) -> 0 | J10: Parcelamento | L10: 300 | N10: =IF($T$1=0,0,L10/$T$1) -> 0.15
B11: Outros bens | D11: 250 | F11: =IF($S$1=0,0,D11/$S$1) -> 0.055555556 | N11: =IF($T$1=0,0,L11/$T$1) -> 0
B12: Veículo | D12: 750 | F12: =IF($S$1=0,0,D12/$S$1) -> 0.16666667 | J12: Outras Dívidas | L12: 500 | N12: =IF($T$1=0,0,L12/$T$1) -> 0.25
F13: =IF($S$1=0,0,D13/$S$1) -> 0 | J13: Cartão de Crédito | L13: 200 | N13: =IF($T$1=0,0,L13/$T$1) -> 0.1
F14: =IF($S$1=0,0,D14/$S$1) -> 0 | N14: =IF($T$1=0,0,L14/$T$1) -> 0
B15: Investimento | D15: 1500 | F15: =IF($S$1=0,0,D15/$S$1) -> 0.33333333 | N15: =IF($T$1=0,0,L15/$T$1) -> 0
B16: Imóvel | D16: 2000 | F16: =IF($S$1=0,0,D16/$S$1) -> 0.44444444 | N16: =IF($T$1=0,0,L16/$T$1) -> 0
F17: =IF($S$1=0,0,D17/$S$1) -> 0 | N17: =IF($T$1=0,0,L17/$T$1) -> 0
F18: =IF($S$1=0,0,D18/$S$1) -> 0 | N18: =IF($T$1=0,0,L18/$T$1) -> 0
F19: =IF($S$1=0,0,D19/$S$1) -> 0 | N19: =IF($T$1=0,0,L19/$T$1) -> 0
F20: =IF($S$1=0,0,D20/$S$1) -> 0 | N20: =IF($T$1=0,0,L20/$T$1) -> 0
F21: =IF($S$1=0,0,D21/$S$1) -> 0 | N21: =IF($T$1=0,0,L21/$T$1) -> 0
F22: =IF($S$1=0,0,D22/$S$1) -> 0 | N22: =IF($T$1=0,0,L22/$T$1) -> 0
F23: =IF($S$1=0,0,D23/$S$1) -> 0 | N23: =IF($T$1=0,0,L23/$T$1) -> 0
F24: =IF($S$1=0,0,D24/$S$1) -> 0 | N24: =IF($T$1=0,0,L24/$T$1) -> 0
F25: =IF($S$1=0,0,D25/$S$1) -> 0 | N25: =IF($T$1=0,0,L25/$T$1) -> 0
F26: =IF($S$1=0,0,D26/$S$1) -> 0 | N26: =IF($T$1=0,0,L26/$T$1) -> 0
F27: =IF($S$1=0,0,D27/$S$1) -> 0 | N27: =IF($T$1=0,0,L27/$T$1) -> 0
F28: =IF($S$1=0,0,D28/$S$1) -> 0 | N28: =IF($T$1=0,0,L28/$T$1) -> 0
... F38: =IF($S$1=0,0,D38/$S$1) -> 0 | N38: =IF($T$1=0,0,L38/$T$1) -> 0

Sheet Investimentos
A1: Investimentos
B8: Tipo | C8: Instituição | D8: Investimento | E8: Valor Investido | F8: valor Atual | G8: Ganho/Perda
B9: Criptomoedas | E9: 1500 | F9: 4000 | G9: =F9-E9 -> 2500 | L9: Total Investido
B10: Ações | E10: 120 | F10: 100 | G10: =F10-E10 -> -20
B11: Fundos Imobiliários | E11: 150 | F11: 180 | G11: =F11-E11 -> 30 | M11: =SUM(E:E) -> 2160
B12: Tesouro Direto | E12: 90 | F12: 70 | G12: =F12-E12 -> -20
B13: ETFs | E13: 300 | F13: 450 | G13: =F13-E13 -> 150
G14: =F14-E14 -> 0
G15: =F15-E15 -> 0 | L15: Valor Atual Total
G16: =F16-E16 -> 0
G17: =F17-E17 -> 0 | M17: =SUM(F:F) -> 4800
G18: =F18-E18 -> 0
G19: =F19-E19 -> 0
G20: =F20-E20 -> 0
G21: =F21-E21 -> 0 | L21: Resultado Total
G22: =F22-E22 -> 0
G23: =F23-E23 -> 0 | M23: =M17-M11 -> 2640
G24: =F24-E24 -> 0
G25: =F25-E25 -> 0
G26: =F26-E26 -> 0
G27: =F27-E27 -> 0
G28: =F28-E28 -> 0
G29: =F29-E29 -> 0
G30: =F30-E30 -> 0
G31: =F31-E31 -> 0
G32: =F32-E32 -> 0
G33: =F33-E33 -> 0
G34: =F34-E34 -> 0
G35: =F35-E35 -> 0
... G38: =F38-E38 -> 0

Sheet Configurações
B1: ATIVOS | D1: PASSIVOS | F1: INVESTIMENTOS
B2: Dinheiro | D2: Cartão de Crédito | F2: Renda Fixa
B3: Investimento | D3: Empréstimo | F3: Tesouro Direto
B4: Veículo | D4: Financiamento | F4: Ações
B5: Imóvel | D5: Parcelamento | F5: Fundos Imobiliários
B6: Outros bens | D6: Outras Dívidas | F6: ETFs
F7: Criptomoedas
F8: Poupança
F9: Outros
